mcred/__init__.py
mcred-1.0.2.dist-info/LICENSE
mcred-1.0.2.dist-info/METADATA
mcred-1.0.2.dist-info/WHEEL
mcred-1.0.2.dist-info/top_level.txt
mcred-1.0.2.dist-info/RECORD
