Metadata-Version: 2.1
Name: mcred
Version: 1.0.2
Summary: manage credentials from remote server
Author: Moses Dastmard
License-File: LICENSE
Requires-Dist: mpath
Requires-Dist: mclass
